django_query_debug/__init__.py
django_query_debug/__version__.py
django_query_debug/apps.py
django_query_debug/mixins.py
django_query_debug/patch.py
django_query_debug/utils.py
django_query_debug-1.0.0.dist-info/LICENSE
django_query_debug-1.0.0.dist-info/METADATA
django_query_debug-1.0.0.dist-info/WHEEL
django_query_debug-1.0.0.dist-info/top_level.txt
django_query_debug-1.0.0.dist-info/RECORD
