Metadata-Version: 2.1
Name: django-query-debug
Version: 1.0.0
Summary: Helper methods and mixins for debugging query issues.
Home-page: https://github.com/RouganStriker/django-query-debug
Author: Kelvin Chan
Author-email: kelvinc.25@gmail.com
License: MIT
Platform: UNKNOWN
Classifier: License :: OSI Approved :: MIT License
Classifier: Programming Language :: Python
Classifier: Programming Language :: Python :: 2
Classifier: Programming Language :: Python :: 2.7
Classifier: Programming Language :: Python :: 3
Classifier: Programming Language :: Python :: 3.6
Classifier: Programming Language :: Python :: Implementation :: CPython
Classifier: Programming Language :: Python :: Implementation :: PyPy
Requires-Python: >=2.7.0
Requires-Dist: depocs
Requires-Dist: django (>=1.11.0)
Requires-Dist: sqlparse
Requires-Dist: six (==1.12.0)
Provides-Extra: sql_formatting
Requires-Dist: pygments ; extra == 'sql_formatting'
